pyqdt/__init__.py
pyqdt/quote_archive.py
pyqdt/quote_base.py
pyqdt/quote_data.py
pyqdt/utils.py
pyqdt/wraps.py
pyqdt/technical_analysis/__init__.py
pyqdt/technical_analysis/arithmetic.py
pyqdt/technical_analysis/energy.py
pyqdt/technical_analysis/moving_average.py
pyqdt/technical_analysis/over_bought_sold.py
pyqdt/technical_analysis/path_lines.py
pyqdt/technical_analysis/trend_lines.py
pyqdt/technical_analysis/turnover.py
pyqdt-0.5.1.dist-info/LICENSE
pyqdt-0.5.1.dist-info/METADATA
pyqdt-0.5.1.dist-info/WHEEL
pyqdt-0.5.1.dist-info/top_level.txt
pyqdt-0.5.1.dist-info/RECORD
